odoo8_addon_website_hr_contact-8.0.1.0.0.99.dev6-py3.8-nspkg.pth
odoo_addons/website_hr_contact/README.rst
odoo_addons/website_hr_contact/__init__.py
odoo_addons/website_hr_contact/__openerp__.py
odoo_addons/website_hr_contact/controllers/__init__.py
odoo_addons/website_hr_contact/controllers/main.py
odoo_addons/website_hr_contact/data/website_hr_contact_data.xml
odoo_addons/website_hr_contact/i18n/ca.po
odoo_addons/website_hr_contact/i18n/da.po
odoo_addons/website_hr_contact/i18n/de.po
odoo_addons/website_hr_contact/i18n/el_GR.po
odoo_addons/website_hr_contact/i18n/es.po
odoo_addons/website_hr_contact/i18n/eu.po
odoo_addons/website_hr_contact/i18n/fi.po
odoo_addons/website_hr_contact/i18n/fr.po
odoo_addons/website_hr_contact/i18n/gl.po
odoo_addons/website_hr_contact/i18n/hr.po
odoo_addons/website_hr_contact/i18n/hr_HR.po
odoo_addons/website_hr_contact/i18n/hu.po
odoo_addons/website_hr_contact/i18n/it.po
odoo_addons/website_hr_contact/i18n/lv.po
odoo_addons/website_hr_contact/i18n/nb.po
odoo_addons/website_hr_contact/i18n/nb_NO.po
odoo_addons/website_hr_contact/i18n/nl.po
odoo_addons/website_hr_contact/i18n/nl_NL.po
odoo_addons/website_hr_contact/i18n/pl.po
odoo_addons/website_hr_contact/i18n/pt.po
odoo_addons/website_hr_contact/i18n/pt_BR.po
odoo_addons/website_hr_contact/i18n/ro.po
odoo_addons/website_hr_contact/i18n/ru.po
odoo_addons/website_hr_contact/i18n/sl.po
odoo_addons/website_hr_contact/i18n/sv.po
odoo_addons/website_hr_contact/i18n/tr.po
odoo_addons/website_hr_contact/i18n/website_hr_contact.pot
odoo_addons/website_hr_contact/static/description/icon.png
odoo_addons/website_hr_contact/static/src/css/website_hr_contact.css
odoo_addons/website_hr_contact/views/website_hr_contact_templates.xml
odoo8_addon_website_hr_contact-8.0.1.0.0.99.dev6.dist-info/METADATA
odoo8_addon_website_hr_contact-8.0.1.0.0.99.dev6.dist-info/WHEEL
odoo8_addon_website_hr_contact-8.0.1.0.0.99.dev6.dist-info/namespace_packages.txt
odoo8_addon_website_hr_contact-8.0.1.0.0.99.dev6.dist-info/top_level.txt
odoo8_addon_website_hr_contact-8.0.1.0.0.99.dev6.dist-info/RECORD
